gtja_vintex_qyt/__init__.py
gtja_vintex_qyt/constants.py
gtja_vintex_qyt/gtja_vintex_qyt.py
gtja_vintex_qyt/gtja_vintex_requests.py
gtja_vintex_qyt/models.py
gtja_vintex_qyt/utils.py
gtja_vintex_qyt/lib/__init__.py
gtja_vintex_qyt/lib/libGtjaCommon.dll
gtja_vintex_qyt/lib/libGtjaCommon.so
gtja_vintex_qyt/lib/vintex.pub
tests/__init__.py
tests/test_utils.py
gtja_vintex_qyt-1.0.6.dist-info/LICENSE
gtja_vintex_qyt-1.0.6.dist-info/METADATA
gtja_vintex_qyt-1.0.6.dist-info/WHEEL
gtja_vintex_qyt-1.0.6.dist-info/top_level.txt
gtja_vintex_qyt-1.0.6.dist-info/RECORD
